sliced/__init__.py
sliced/base.py
sliced/save.py
sliced/sir.py
sliced/version.py
sliced/whiten.py
sliced/datasets/__init__.py
sliced/datasets/athletes.py
sliced/datasets/banknote.py
sliced/datasets/base.py
sliced/datasets/synthetic.py
sliced/datasets/data/athletes.csv
sliced/datasets/data/banknote.csv
sliced/externals/__init__.py
sliced/externals/sklearn_partial.py
sliced/test/__init__.py
sliced/test/test_save.py
sliced/test/test_sir.py
sliced/test/test_sklearn_compatibility.py
sliced/test/test_slice.py
sliced-0.7.0.dist-info/DESCRIPTION.rst
sliced-0.7.0.dist-info/METADATA
sliced-0.7.0.dist-info/RECORD
sliced-0.7.0.dist-info/WHEEL
sliced-0.7.0.dist-info/metadata.json
sliced-0.7.0.dist-info/top_level.txt
