Metadata-Version: 2.0
Name: sliced
Version: 0.7.0
Summary: Toolbox for sufficient dimension reduction (SDR).
Home-page: https://joshloyal.github.io/sliced
Author: Joshua D. Loyal
Author-email: jloyal25@gmail.com
License: MIT
Download-URL: https://pypi.org/project/sliced/#files
Platform: UNKNOWN
Classifier: Intended Audience :: Science/Research
Classifier: Intended Audience :: Developers
Classifier: License :: OSI Approved :: MIT License
Classifier: Programming Language :: Python
Classifier: Topic :: Software Development
Classifier: Topic :: Scientific/Engineering
Classifier: Operating System :: Microsoft :: Windows
Classifier: Operating System :: POSIX
Classifier: Operating System :: Unix
Classifier: Operating System :: MacOS
Classifier: Programming Language :: Python :: 2
Classifier: Programming Language :: Python :: 2.7
Classifier: Programming Language :: Python :: 3
Classifier: Programming Language :: Python :: 3.5
Classifier: Programming Language :: Python :: 3.6
Requires-Dist: scipy (>=0.13.3)
Requires-Dist: numpy (>=1.8.2)
Requires-Dist: scikit-learn (>=0.17)
Provides-Extra: test
Requires-Dist: pytest; extra == 'test'
Requires-Dist: pytest-pep8; extra == 'test'
Requires-Dist: pytest-cov; extra == 'test'
Requires-Dist: nose (>=1.1.2); extra == 'test'
